LICENSE.txt
MANIFEST.in
README.rst
setup.cfg
setup.py
ckeditor_emencia/__init__.py
ckeditor_emencia/models.py
ckeditor_emencia/urls.py
ckeditor_emencia/views.py
ckeditor_emencia.egg-info/PKG-INFO
ckeditor_emencia.egg-info/SOURCES.txt
ckeditor_emencia.egg-info/dependency_links.txt
ckeditor_emencia.egg-info/not-zip-safe
ckeditor_emencia.egg-info/requires.txt
ckeditor_emencia.egg-info/top_level.txt
ckeditor_emencia/editor-site-templates/grid_row_3_flyers.html
ckeditor_emencia/editor-site-templates/grid_row_4_flyers.html
ckeditor_emencia/editor-site-templates/intro_type-1.html
ckeditor_emencia/editor-site-templates/intro_type-2.html
ckeditor_emencia/editor-site-templates/intro_type-3.html
ckeditor_emencia/editor-site-templates/manifest.json
ckeditor_emencia/editor-site-templates/mosaic-rows.html
ckeditor_emencia/static/ckeditor_emencia/button-dropdown.png
ckeditor_emencia/static/ckeditor_emencia/grid_row_3_flyers.png
ckeditor_emencia/static/ckeditor_emencia/grid_row_4_flyers.png
ckeditor_emencia/static/ckeditor_emencia/intro_type-1.png
ckeditor_emencia/static/ckeditor_emencia/intro_type-2.png
ckeditor_emencia/static/ckeditor_emencia/intro_type-3.png
ckeditor_emencia/static/ckeditor_emencia/mosaic-rows.png